buildPackage/__init__.py
complex_stt-0.1.dist-info/METADATA
complex_stt-0.1.dist-info/WHEEL
complex_stt-0.1.dist-info/top_level.txt
complex_stt-0.1.dist-info/RECORD
